Metadata-Version: 1.1
Name: dingtalk
Version: 0.0.4
Summary: Python SDK for DingTalk
Home-page: https://github.com/ahlfors/dingtalk
Author: ahlfors
Author-email: ahlforslee@gmail.com
License: MIT
Keywords: DingTalk SDK
Platform: UNKNOWN
Classifier: Development Status :: 3 - Alpha
Classifier: Intended Audience :: Developers
Classifier: Topic :: Software Development :: Build Tools
Classifier: License :: OSI Approved :: MIT License
Classifier: Programming Language :: Python :: 2
Classifier: Programming Language :: Python :: 2.6
Classifier: Programming Language :: Python :: 2.7
Classifier: Programming Language :: Python :: 3
Classifier: Programming Language :: Python :: 3.2
Classifier: Programming Language :: Python :: 3.3
Classifier: Programming Language :: Python :: 3.4
Classifier: Programming Language :: Python :: 3.5
